README.md
setup.py
src/benchmarkai/__init__.py
src/benchmarkai_client_lib.egg-info/PKG-INFO
src/benchmarkai_client_lib.egg-info/SOURCES.txt
src/benchmarkai_client_lib.egg-info/dependency_links.txt
src/benchmarkai_client_lib.egg-info/requires.txt
src/benchmarkai_client_lib.egg-info/top_level.txt